perdu/__init__.py
perdu/db.py
perdu/filesystem.py
perdu/logs.py
perdu/semantic_web.py
perdu/utils.py
perdu/webapp.py
perdu/assets/css/customizations.css
perdu/assets/css/normalize.css
perdu/assets/css/skeleton.css
perdu/assets/images/favicon.ico
perdu/assets/templates/file.html
perdu/assets/templates/footer.html
perdu/assets/templates/header.html
perdu/assets/templates/index.html
perdu/assets/templates/search.html
perdu/assets/templates/search_result.html
perdu/data/__init__.py
perdu/data/gs1.json.bz2
perdu/data/naics.json.bz2
perdu/data/useeio.json.bz2
perdu/ingestion/__init__.py
perdu/ingestion/csv.py
perdu/searching/__init__.py
perdu/searching/gs1.py
perdu/searching/naics.py
perdu/searching/useeio.py
perdu/searching/utils.py
perdu-0.1.1.dist-info/LICENSE
perdu-0.1.1.dist-info/METADATA
perdu-0.1.1.dist-info/WHEEL
perdu-0.1.1.dist-info/entry_points.txt
perdu-0.1.1.dist-info/top_level.txt
perdu-0.1.1.dist-info/RECORD
