Metadata-Version: 2.1
Name: perdu
Version: 0.1.1
Summary: Python library and webapp for searching standard industry and product classifiers
Home-page: https://github.com/cmutel/perdu
Author: Chris Mutel
Author-email: cmutel@gmail.com
License: BSD 3-clause
Platform: UNKNOWN
Classifier: Intended Audience :: End Users/Desktop
Classifier: Intended Audience :: Developers
Classifier: Intended Audience :: Science/Research
Classifier: License :: OSI Approved :: BSD License
Classifier: Operating System :: MacOS :: MacOS X
Classifier: Operating System :: Microsoft :: Windows
Classifier: Operating System :: POSIX
Classifier: Programming Language :: Python
Classifier: Programming Language :: Python :: 3
Classifier: Programming Language :: Python :: 3.5
Classifier: Programming Language :: Python :: 3.6
Classifier: Programming Language :: Python :: 3.7
Classifier: Topic :: Scientific/Engineering :: Information Analysis
Requires-Dist: appdirs
Requires-Dist: docopt
Requires-Dist: flask
Requires-Dist: peewee
Requires-Dist: rdflib
Requires-Dist: rdflib-jsonld
Requires-Dist: whoosh
